pacotebanco/Armazenamento.py
pacotebanco/Consulta.py
pacotebanco/Interacao.py
pacotebanco/__init__.py
pacotebanco/main.py
bancodeusuarios-0.0.1.dist-info/LICENSE
bancodeusuarios-0.0.1.dist-info/METADATA
bancodeusuarios-0.0.1.dist-info/WHEEL
bancodeusuarios-0.0.1.dist-info/top_level.txt
bancodeusuarios-0.0.1.dist-info/RECORD
