Metadata-Version: 2.1
Name: bancodeusuarios
Version: 0.0.1
Summary: Pacote Python para cadastrar, armazenar e consultar usuários em um sistema.
Home-page: https://github.com/CaioJohnston
Author: Caio Johnston Soares
Author-email: caio21070002@aluno.cesupa.br
License: MIT License
Keywords: Pacote
Platform: UNKNOWN
License-File: LICENSE
